.gitignore
LICENSE
README.md
README.rst
build.sh
init_this_project.sh
requirements.txt
setup.py
lian/__init__.py
lian/config.py
lian/daemon.py
lian/default_settings.py
lian/dispatcher.py
lian/mongo.py
lian/mongo_monitoring.py
lian/mq.py
lian/redis.py
lian/settings.py
lian/singleton.py
lian/ssh.py
lian/ssh_deploy.py
lian/weakref_backports.py
lian.egg-info/PKG-INFO
lian.egg-info/SOURCES.txt
lian.egg-info/dependency_links.txt
lian.egg-info/requires.txt
lian.egg-info/top_level.txt
lian/orm/__init__.py
lian/orm/db.py
lian/orm/sql.py
lian/utils/__init__.py
lian/utils/array.py
lian/utils/chinese.py
lian/utils/compute.py
lian/utils/fs.py
lian/utils/hash.py
lian/utils/inspect.py
lian/utils/json_encoder.py
lian/utils/logger.py
lian/utils/random_string.py
lian/utils/smtplib.py
lian/utils/thread_context.py
lian/utils/time.py
lian/utils/tornado_validation.py
lian/utils/words.py